swagger_doc/__init__.py
swagger_doc/builders.py
swagger_doc/handlers.py
swagger_doc/models.py
swagger_doc/utils.py
swagger_doc/static/redoc_ui/redoc.css
swagger_doc/static/redoc_ui/redoc.js
swagger_doc/static/redoc_ui/ui.jinja2
swagger_doc/static/swagger_ui/swagger-ui-bundle.js
swagger_doc/static/swagger_ui/swagger-ui-standalone-preset.js
swagger_doc/static/swagger_ui/swagger-ui.css
swagger_doc/static/swagger_ui/ui.jinja2
swagger_doc/templates/swagger.yaml
swagger_doc-0.0.12.dist-info/licenses/LICENSE
swagger_doc-0.0.12.dist-info/METADATA
swagger_doc-0.0.12.dist-info/WHEEL
swagger_doc-0.0.12.dist-info/top_level.txt
swagger_doc-0.0.12.dist-info/RECORD
