Metadata-Version: 2.4
Name: swagger-doc
Version: 0.0.12
Summary: swagger doc for tornado
Author-email: aaashuai <nsity223@gmail.com>
License: Apache 2.0
Classifier: Programming Language :: Python :: 3.9
Classifier: Programming Language :: Python :: 3.10
Classifier: Programming Language :: Python :: 3.11
Classifier: License :: OSI Approved :: Apache Software License
Classifier: Operating System :: OS Independent
Requires-Python: >=3.9
License-File: LICENSE
Requires-Dist: pydantic>=2.11.3
Requires-Dist: tornado>=6.0.1
Requires-Dist: Jinja2>=2
Requires-Dist: PyYaml>=5
Dynamic: license-file
